carbonplan_forests/__init__.py
carbonplan_forests/prepare.py
carbonplan_forests/utils.py
carbonplan_forests/data/__init__.py
carbonplan_forests/data/catalog.yaml
carbonplan_forests/data/nlcd_albedo_conversions.csv
carbonplan_forests/fit/__init__.py
carbonplan_forests/fit/biomass.py
carbonplan_forests/fit/fire.py
carbonplan_forests/fit/hurdle.py
carbonplan_forests/fit/interp.py
carbonplan_forests/load/__init__.py
carbonplan_forests/load/cmip.py
carbonplan_forests/load/fia.py
carbonplan_forests/load/mtbs.py
carbonplan_forests/load/nftd.py
carbonplan_forests/load/nlcd.py
carbonplan_forests/load/terraclim.py
carbonplan_forests/plot/__init__.py
carbonplan_forests/plot/carto.py
carbonplan_forests/plot/fire.py
carbonplan_forests/plot/line.py
carbonplan_forests/plot/xy.py
carbonplan_forests/preprocess/__init__.py
carbonplan_forests/preprocess/fia.py
carbonplan_forests/setup/__init__.py
carbonplan_forests/setup/loading.py
carbonplan_forests/setup/plotting.py
carbonplan_forests-0.1.2.dist-info/LICENSE
carbonplan_forests-0.1.2.dist-info/METADATA
carbonplan_forests-0.1.2.dist-info/WHEEL
carbonplan_forests-0.1.2.dist-info/top_level.txt
carbonplan_forests-0.1.2.dist-info/RECORD
